kotti_toolkit/__init__.py
kotti_toolkit/__init__.pyc
kotti_toolkit/renderers.py
kotti_toolkit/renderers.pyc
kotti_toolkit/security.py
kotti_toolkit/security.pyc
kotti_toolkit/util.py
kotti_toolkit/util.pyc
kotti_toolkit/locale/.gitkeep
kotti_toolkit/scripts/__init__.py
kotti_toolkit/scripts/__init__.pyc
kotti_toolkit/scripts/funcs.py
kotti_toolkit/scripts/funcs.pyc
kotti_toolkit/scripts/importer.py
kotti_toolkit/scripts/importer.pyc
kotti_toolkit/scripts/manage_users.py
kotti_toolkit/scripts/manage_users.pyc
kotti_toolkit/tests/conftest.py
kotti_toolkit/tests/test_functional.py
kotti_toolkit/tests/test_resources.py
kotti_toolkit/tests/test_view.py
kotti_toolkit-1.0.2.dist-info/METADATA
kotti_toolkit-1.0.2.dist-info/RECORD
kotti_toolkit-1.0.2.dist-info/WHEEL
kotti_toolkit-1.0.2.dist-info/entry_points.txt
kotti_toolkit-1.0.2.dist-info/top_level.txt
scripts/__init__.py
scripts/funcs.py
scripts/importer.py
scripts/manage_users.py
