Metadata-Version: 2.1
Name: kotti-toolkit
Version: 1.0.2
Summary: Utilities for Kotti
Home-page: https://github.com/Collective-Kotti/kotti_toolkit
Author: Oshane Bailey
Author-email: b4.oshany@gmail.com
License: BSD-derived (http://www.repoze.org/LICENSE.txt)
Keywords: kotti tools utils web cms wcms pylons pyramid
Platform: UNKNOWN
Classifier: Programming Language :: Python
Classifier: Programming Language :: Python :: 2.6
Classifier: Programming Language :: Python :: 2.7
Classifier: Framework :: Pylons
Classifier: Topic :: Internet :: WWW/HTTP
Classifier: Topic :: Internet :: WWW/HTTP :: Dynamic Content
Classifier: Topic :: Internet :: WWW/HTTP :: WSGI :: Application
Classifier: License :: Repoze Public License
Requires-Dist: click (>=6.6)
Requires-Dist: Kotti (>=1.0.0)
Requires-Dist: kotti-tinymce
Requires-Dist: progress
